reportermd/__init__.py
reportermd/__init__.pyc
reportermd/cli.py
reportermd/cli.pyc
reportermd/import_to_dayone.sh
reportermd/templates/__init__.py
reportermd/templates/__init__.pyc
reportermd/templates/snapshot.md
reportermd-0.0.6.dist-info/DESCRIPTION.rst
reportermd-0.0.6.dist-info/METADATA
reportermd-0.0.6.dist-info/RECORD
reportermd-0.0.6.dist-info/WHEEL
reportermd-0.0.6.dist-info/entry_points.txt
reportermd-0.0.6.dist-info/metadata.json
reportermd-0.0.6.dist-info/top_level.txt
