Metadata-Version: 2.0
Name: reportermd
Version: 0.0.6
Summary: Convert your Reporter App dates to MD then import to Day One
Home-page: https://github.com/sambev/reportermd
Author: Sam Beveridge
Author-email: sam.bev87@gmail.com
License: MIT
Platform: UNKNOWN
Requires-Dist: Jinja2 (>=2.8)
Requires-Dist: python-dateutil (==2.4.2)
